{
  "createdAt": "2020-10-12T15:38:17.000Z",
  "updatedAt": "2022-05-14T16:04:21.000Z",
  "checkedAt": "2022-05-14T16:04:21.000Z",
  "id": 1454,
  "type": "anime",
  "title": "Kemonozume",
  "altTitle": [
    "The Beast Claw",
    "ケモノヅメ"
  ],
  "url": "https://myanimelist.net/anime/1454/Kemonozume",
  "image": "https://cdn.myanimelist.net/images/anime/3/86766.jpg",
  "category": "TV",
  "hentai": false,
  "externalLinks": [
    {
      "site": "animedb",
      "url": "http://anidb.info/perl-bin/animedb.pl?show=anime&aid=4392"
    },
    {
      "site": "animenewsnetwork",
      "url": "http://www.animenewsnetwork.com/encyclopedia/anime.php?id=6722"
    },
    {
      "site": "wikipedia",
      "url": "http://en.wikipedia.org/wiki/Kemonozume"
    }
  ],
  "legalLinks": [],
  "deletedAt": null,
  "anidbId": 4392,
  "Pages": {
    "9anime": {
      "pm66": {
        "createdAt": "2020-10-12T15:54:48.000Z",
        "updatedAt": "2021-05-20T15:21:52.000Z",
        "checkedAt": null,
        "id": 7993,
        "identifier": "pm66",
        "type": "anime",
        "page": "9anime",
        "title": "Kemonozume",
        "url": "https://9anime.to/watch/kemonozume.pm66",
        "image": "https://images2-focus-opensocial.googleusercontent.com/gadgets/proxy?container=focus&amp;gadget=a&amp;no_expand=1&amp;refresh=604800&amp;url=http://2.bp.blogspot.com/-8TCsu2p53wI/V7mtUXc3WII/AAAAAAAA4tM/kyzPchvyuFA/s0/",
        "hentai": false,
        "sticky": false,
        "active": true,
        "actorId": null,
        "malId": 1454,
        "aniId": 1454,
        "deletedAt": null
      }
    },
    "Gogoanime": {
      "kemonozume": {
        "createdAt": "2020-10-12T16:00:58.000Z",
        "updatedAt": "2021-05-20T15:21:54.000Z",
        "checkedAt": null,
        "id": 18777,
        "identifier": "kemonozume",
        "type": "anime",
        "page": "Gogoanime",
        "title": "Kemonozume",
        "url": "https://gogoanime.vc/category/kemonozume",
        "image": "https://cdnimg.xyz/cover/kemonozume.png",
        "hentai": false,
        "sticky": false,
        "active": true,
        "actorId": null,
        "malId": 1454,
        "aniId": 1454,
        "deletedAt": null
      }
    },
    "AniMixPlay": {
      "1454": {
        "identifier": "1454",
        "malId": 1454,
        "type": "anime",
        "page": "AniMixPlay",
        "title": "Kemonozume",
        "url": "https://animixplay.to/anime/1454"
      }
    },
    "YugenAnime": {
      "1372": {
        "identifier": "1372",
        "malId": 1454,
        "type": "anime",
        "page": "YugenAnime",
        "title": "Kemonozume",
        "url": "https://yugen.to/anime/1372/kemonozume/"
      }
    }
  }
}