{
  "createdAt": "2020-10-12T15:38:22.000Z",
  "updatedAt": "2022-05-14T15:50:26.000Z",
  "checkedAt": "2022-05-14T15:50:26.000Z",
  "id": 1860,
  "type": "anime",
  "title": "Tokyo Majin Gakuen Kenpucho: Tou",
  "altTitle": [
    "Tokyo Majin Gakuen Kenpuchou",
    "Tokyo Majin",
    "東京魔人學園剣風帖　龖（トウ）"
  ],
  "url": "https://myanimelist.net/anime/1860/Tokyo_Majin_Gakuen_Kenpucho__Tou",
  "image": "https://cdn.myanimelist.net/images/anime/1894/113730.jpg",
  "category": "TV",
  "hentai": false,
  "externalLinks": [
    {
      "site": "officialsite",
      "url": "http://www.majin.tv/"
    },
    {
      "site": "animedb",
      "url": "http://anidb.info/perl-bin/animedb.pl?show=anime&aid=4799"
    },
    {
      "site": "animenewsnetwork",
      "url": "http://www.animenewsnetwork.com/encyclopedia/anime.php?id=7123"
    },
    {
      "site": "wikipedia",
      "url": "http://en.wikipedia.org/wiki/Tokyo_Majin_Gakuen_Kenpuch%C5%8D:_T%C5%8D"
    }
  ],
  "legalLinks": [
    {
      "site": "crunchyroll",
      "url": "http://www.crunchyroll.com/series-273941"
    },
    {
      "site": "funimation",
      "url": "https://www.funimation.com/shows/tokyo-majin"
    }
  ],
  "deletedAt": null,
  "anidbId": 4799,
  "Pages": {
    "9anime": {
      "59om": {
        "createdAt": "2020-10-12T15:50:26.000Z",
        "updatedAt": "2021-05-20T15:21:51.000Z",
        "checkedAt": null,
        "id": 2612,
        "identifier": "59om",
        "type": "anime",
        "page": "9anime",
        "title": "Tokyo Majin Gakuen Kenpucho: Tou",
        "url": "https://9anime.to/watch/tokyo-majin-gakuen-kenpucho-tou.59om",
        "image": "https://images2-focus-opensocial.googleusercontent.com/gadgets/proxy?container=focus&amp;gadget=a&amp;no_expand=1&amp;refresh=604800&amp;url=http://2.bp.blogspot.com/-8T7K7k3a15Y/V7K1Dn6I1vI/AAAAAAAA3cs/R6u0mrNSXvw/s0/",
        "hentai": false,
        "sticky": false,
        "active": true,
        "actorId": null,
        "malId": 1860,
        "aniId": 1860,
        "deletedAt": null
      },
      "z8zp": {
        "createdAt": "2020-10-12T15:57:08.000Z",
        "updatedAt": "2021-05-20T15:21:53.000Z",
        "checkedAt": null,
        "id": 11108,
        "identifier": "z8zp",
        "type": "anime",
        "page": "9anime",
        "title": "Tokyo Majin Gakuen Kenpucho: Tou (Dub)",
        "url": "https://9anime.to/watch/tokyo-majin-gakuen-kenpucho-tou-dub.z8zp",
        "image": "https://images2-focus-opensocial.googleusercontent.com/gadgets/proxy?container=focus&amp;gadget=a&amp;no_expand=1&amp;refresh=604800&amp;url=http://2.bp.blogspot.com/-yVEVOH0DQsU/V_cjjBPAm0I/AAAAAAABElw/tEDRoQxpURw/s0/",
        "hentai": false,
        "sticky": false,
        "active": true,
        "actorId": null,
        "malId": 1860,
        "aniId": 1860,
        "deletedAt": null
      }
    },
    "Gogoanime": {
      "tokyo-majin-gakuen-kenpucho-tou-dub": {
        "createdAt": "2020-10-12T16:02:07.000Z",
        "updatedAt": "2021-05-20T15:21:55.000Z",
        "checkedAt": null,
        "id": 21163,
        "identifier": "tokyo-majin-gakuen-kenpucho-tou-dub",
        "type": "anime",
        "page": "Gogoanime",
        "title": "Tokyo Majin Gakuen Kenpucho: Tou (Dub)",
        "url": "https://gogoanime.vc/category/tokyo-majin-gakuen-kenpucho-tou-dub",
        "image": "https://gogocdn.net/cover/tokyo-majin-gakuen-kenpucho-tou-dub.png",
        "hentai": false,
        "sticky": false,
        "active": true,
        "actorId": null,
        "malId": 1860,
        "aniId": 1860,
        "deletedAt": null
      },
      "tokyo-majin-gakuen-kenpuchou": {
        "createdAt": "2020-10-12T16:02:07.000Z",
        "updatedAt": "2021-05-20T15:21:55.000Z",
        "checkedAt": null,
        "id": 21164,
        "identifier": "tokyo-majin-gakuen-kenpuchou",
        "type": "anime",
        "page": "Gogoanime",
        "title": "Tokyo Majin Gakuen Kenpuchou",
        "url": "https://gogoanime.vc/category/tokyo-majin-gakuen-kenpuchou",
        "image": "https://gogocdn.net/images/anime/T/Tokyo-Majin-Gakuen-Kenpuchou.jpg",
        "hentai": false,
        "sticky": false,
        "active": true,
        "actorId": null,
        "malId": 1860,
        "aniId": 1860,
        "deletedAt": null
      }
    },
    "AniMixPlay": {
      "1860": {
        "identifier": "1860",
        "malId": 1860,
        "type": "anime",
        "page": "AniMixPlay",
        "title": "Tokyo Majin Gakuen Kenpucho: Tou",
        "url": "https://animixplay.to/anime/1860"
      }
    },
    "YugenAnime": {
      "2814": {
        "identifier": "2814",
        "malId": 1860,
        "type": "anime",
        "page": "YugenAnime",
        "title": "Tokyo Majin Gakuen Kenpucho: Tou",
        "url": "https://yugen.to/anime/2814/tokyo-majin-gakuen-kenpucho-tou/"
      }
    }
  }
}