{
  "createdAt": "2020-10-12T15:38:26.000Z",
  "updatedAt": "2022-05-14T19:12:17.000Z",
  "checkedAt": "2022-05-14T19:12:17.000Z",
  "id": 2144,
  "type": "anime",
  "title": "Naruto Movie 3: Dai Koufun! Mikazuki Jima no Animaru Panikku Dattebayo!",
  "altTitle": [
    "Naruto Movie Volume 3",
    "Naruto: Gekijouban Naruto: Dai Koufun! Mikazuki-jima no Animal Panic Datte ba yo!",
    "Naruto the Movie 3: Guardians of the Crescent Moon Kingdom",
    "劇場版 NARUTO -ナルト- 大興奮!みかづき島のアニマル騒動だってばよ"
  ],
  "url": "https://myanimelist.net/anime/2144/Naruto_Movie_3__Dai_Koufun_Mikazuki_Jima_no_Animaru_Panikku_Dattebayo",
  "image": "https://cdn.myanimelist.net/images/anime/6/76017.jpg",
  "category": "Movie",
  "hentai": false,
  "externalLinks": [
    {
      "site": "officialsite",
      "url": "http://www.naruto-movie.com/"
    },
    {
      "site": "animedb",
      "url": "http://anidb.info/perl-bin/animedb.pl?show=anime&aid=4421"
    },
    {
      "site": "animenewsnetwork",
      "url": "http://www.animenewsnetwork.com/encyclopedia/anime.php?id=6602"
    },
    {
      "site": "wikipedia",
      "url": "http://en.wikipedia.org/wiki/Naruto_the_Movie:_Guardians_of_the_Crescent_Moon_Kingdom"
    }
  ],
  "legalLinks": [
    {
      "site": "crunchyroll",
      "url": "http://www.crunchyroll.com/series-278869"
    },
    {
      "site": "netflix",
      "url": "https://www.netflix.com/"
    }
  ],
  "deletedAt": null,
  "anidbId": 4421,
  "Pages": {
    "9anime": {
      "4jox": {
        "createdAt": "2020-10-12T15:50:04.000Z",
        "updatedAt": "2021-05-20T15:21:50.000Z",
        "checkedAt": null,
        "id": 2231,
        "identifier": "4jox",
        "type": "anime",
        "page": "9anime",
        "title": "Naruto Movie 3: Dai Koufun! Mikazuki Jima no Animaru Panikku Dattebayo!",
        "url": "https://9anime.to/watch/naruto-movie-3-dai-koufun-mikazuki-jima-no-animaru-panikku-dattebayo.4jox",
        "image": "https://images2-focus-opensocial.googleusercontent.com/gadgets/proxy?container=focus&amp;gadget=a&amp;no_expand=1&amp;refresh=604800&amp;url=http://2.bp.blogspot.com/-wSiFrKqlxcw/V6eDjKuU4eI/AAAAAAAA1JU/nadTkUtG4js/s0/",
        "hentai": false,
        "sticky": false,
        "active": true,
        "actorId": null,
        "malId": 2144,
        "aniId": 2144,
        "deletedAt": null
      },
      "8l8n": {
        "createdAt": "2020-10-12T15:51:29.000Z",
        "updatedAt": "2021-05-20T15:21:51.000Z",
        "checkedAt": null,
        "id": 3890,
        "identifier": "8l8n",
        "type": "anime",
        "page": "9anime",
        "title": "Naruto Movie 3: Dai Koufun! Mikazuki Jima no Animaru Panikku Dattebayo! (Dub)",
        "url": "https://9anime.to/watch/naruto-movie-3-dai-koufun-mikazuki-jima-no-animaru-panikku-dattebayo-dub.8l8n",
        "image": "https://images2-focus-opensocial.googleusercontent.com/gadgets/proxy?container=focus&amp;gadget=a&amp;no_expand=1&amp;refresh=604800&amp;url=http://2.bp.blogspot.com/-cBf6uWPtORk/V_eC0H1M48I/AAAAAAABE2M/Vw5RHrrHVrA/s0/",
        "hentai": false,
        "sticky": false,
        "active": true,
        "actorId": null,
        "malId": 2144,
        "aniId": 2144,
        "deletedAt": null
      }
    },
    "Gogoanime": {
      "naruto-movie-3-dai-koufun-mikazukijima-no-animal-panic-datte-ba-yo": {
        "createdAt": "2020-10-12T16:01:23.000Z",
        "updatedAt": "2021-05-20T15:21:54.000Z",
        "checkedAt": null,
        "id": 19653,
        "identifier": "naruto-movie-3-dai-koufun-mikazukijima-no-animal-panic-datte-ba-yo",
        "type": "anime",
        "page": "Gogoanime",
        "title": "Naruto Movie 3: Dai Koufun! Mikazukijima no Animal Panic Datte ba yo!",
        "url": "https://gogoanime.vc/category/naruto-movie-3-dai-koufun-mikazukijima-no-animal-panic-datte-ba-yo",
        "image": "https://gogocdn.net/images/anime/N/Naruto-movie-3.jpg",
        "hentai": false,
        "sticky": false,
        "active": true,
        "actorId": null,
        "malId": 2144,
        "aniId": 2144,
        "deletedAt": null
      },
      "naruto-the-movie-3-guardians-of-the-crescent-moon-kingdom-dub": {
        "createdAt": "2021-01-29T06:18:00.000Z",
        "updatedAt": "2021-05-20T15:25:21.000Z",
        "checkedAt": null,
        "id": 34321,
        "identifier": "naruto-the-movie-3-guardians-of-the-crescent-moon-kingdom-dub",
        "type": "anime",
        "page": "Gogoanime",
        "title": "Naruto the Movie 3: Guardians of the Crescent Moon Kingdom (Dub)",
        "url": "https://gogoanime.vc/category/naruto-the-movie-3-guardians-of-the-crescent-moon-kingdom-dub",
        "image": "https://gogocdn.net/cover/naruto-the-movie-3-guardians-of-the-crescent-moon-kingdom-dub.png",
        "hentai": false,
        "sticky": false,
        "active": true,
        "actorId": null,
        "malId": 2144,
        "aniId": 2144,
        "deletedAt": null
      }
    },
    "animepahe": {
      "538": {
        "identifier": "538",
        "malId": 2144,
        "type": "anime",
        "page": "animepahe",
        "title": "Naruto Movie 3: Dai Koufun! Mikazuki Jima no Animaru Panikku Dattebayo!",
        "url": "https://animepahe.com/a/538"
      }
    },
    "AniMixPlay": {
      "2144": {
        "identifier": "2144",
        "malId": 2144,
        "type": "anime",
        "page": "AniMixPlay",
        "title": "Naruto Movie 3: Dai Koufun! Mikazuki Jima no Animaru Panikku Dattebayo!",
        "url": "https://animixplay.to/anime/2144"
      }
    },
    "YugenAnime": {
      "3930": {
        "identifier": "3930",
        "malId": 2144,
        "type": "anime",
        "page": "YugenAnime",
        "title": "Naruto Movie 3: Dai Koufun! Mikazuki Jima no Animaru Panikku Dattebayo!",
        "url": "https://yugen.to/anime/3930/naruto-movie-3-dai-koufun-mikazukijima-no-animal-panic-datte-ba-yo/"
      }
    },
    "Zoro": {
      "4005": {
        "identifier": "4005",
        "malId": 2144,
        "type": "anime",
        "page": "Zoro",
        "title": "Naruto the Movie 3: Guardians of the Crescent Moon Kingdom",
        "url": "https://zoro.to/naruto-the-movie-3-guardians-of-the-crescent-moon-kingdom-4005"
      }
    }
  }
}