{
  "createdAt": "2020-10-12T15:39:26.000Z",
  "updatedAt": "2022-05-14T18:10:35.000Z",
  "checkedAt": "2022-05-14T18:10:35.000Z",
  "id": 22687,
  "type": "anime",
  "title": "Terra Formars",
  "altTitle": [
    "Terraformars",
    "TERRA FORMARS [テラフォーマーズ]"
  ],
  "url": "https://myanimelist.net/anime/22687/Terra_Formars",
  "image": "https://cdn.myanimelist.net/images/anime/2/67117.jpg",
  "category": "TV",
  "hentai": false,
  "externalLinks": [
    {
      "site": "officialsite",
      "url": "http://www.terraformars.tv/annex1/"
    },
    {
      "site": "animedb",
      "url": "http://anidb.info/perl-bin/animedb.pl?show=anime&aid=10439"
    },
    {
      "site": "animenewsnetwork",
      "url": "http://www.animenewsnetwork.com/encyclopedia/anime.php?id=16090"
    },
    {
      "site": "wikipedia",
      "url": "http://en.wikipedia.org/wiki/Terra_Formars"
    }
  ],
  "legalLinks": [
    {
      "site": "crunchyroll",
      "url": "http://www.crunchyroll.com/series-263081"
    },
    {
      "site": "funimation",
      "url": "https://www.funimation.com/shows/terraformars"
    },
    {
      "site": "netflix",
      "url": "https://www.netflix.com/"
    }
  ],
  "deletedAt": null,
  "anidbId": 10439,
  "Pages": {
    "9anime": {
      "ll56": {
        "createdAt": "2020-10-12T15:53:05.000Z",
        "updatedAt": "2021-05-20T15:21:51.000Z",
        "checkedAt": null,
        "id": 6052,
        "identifier": "ll56",
        "type": "anime",
        "page": "9anime",
        "title": "Terra Formars",
        "url": "https://9anime.to/watch/terra-formars.ll56",
        "image": "https://images2-focus-opensocial.googleusercontent.com/gadgets/proxy?container=focus&amp;gadget=a&amp;no_expand=1&amp;refresh=604800&amp;url=http://2.bp.blogspot.com/-9g58FJadmck/V5Owx16LVNI/AAAAAAAAxhM/u_svRnsnbMg/s0/",
        "hentai": false,
        "sticky": false,
        "active": true,
        "actorId": null,
        "malId": 22687,
        "aniId": 20629,
        "deletedAt": null
      }
    },
    "Gogoanime": {
      "terra-formars": {
        "createdAt": "2020-10-12T16:02:03.000Z",
        "updatedAt": "2021-05-20T15:21:55.000Z",
        "checkedAt": null,
        "id": 21015,
        "identifier": "terra-formars",
        "type": "anime",
        "page": "Gogoanime",
        "title": "Terra Formars",
        "url": "https://gogoanime.vc/category/terra-formars",
        "image": "https://gogocdn.net/images/fall/Terra Formars.jpg",
        "hentai": false,
        "sticky": false,
        "active": true,
        "actorId": null,
        "malId": 22687,
        "aniId": 20629,
        "deletedAt": null
      },
      "terra-formars-dub": {
        "createdAt": "2020-10-12T16:02:03.000Z",
        "updatedAt": "2021-05-20T15:21:55.000Z",
        "checkedAt": null,
        "id": 21016,
        "identifier": "terra-formars-dub",
        "type": "anime",
        "page": "Gogoanime",
        "title": "Terra Formars (Dub)",
        "url": "https://gogoanime.vc/category/terra-formars-dub",
        "image": "https://gogocdn.net/cover/terra-formars-dub.png",
        "hentai": false,
        "sticky": false,
        "active": true,
        "actorId": null,
        "malId": 22687,
        "aniId": 20629,
        "deletedAt": null
      },
      "terra-formars-ova": {
        "createdAt": "2020-10-12T16:02:03.000Z",
        "updatedAt": "2021-05-20T15:21:55.000Z",
        "checkedAt": null,
        "id": 21017,
        "identifier": "terra-formars-ova",
        "type": "anime",
        "page": "Gogoanime",
        "title": "Terra Formars OVA",
        "url": "https://gogoanime.vc/category/terra-formars-ova",
        "image": "https://gogocdn.net/images/summer/150647.jpg",
        "hentai": false,
        "sticky": false,
        "active": true,
        "actorId": null,
        "malId": 22687,
        "aniId": 20629,
        "deletedAt": null
      }
    },
    "animepahe": {
      "1747": {
        "identifier": "1747",
        "malId": 22687,
        "type": "anime",
        "page": "animepahe",
        "title": "Terra Formars",
        "url": "https://animepahe.com/a/1747"
      }
    },
    "AniMixPlay": {
      "22687": {
        "identifier": "22687",
        "malId": 22687,
        "type": "anime",
        "page": "AniMixPlay",
        "title": "Terra Formars",
        "url": "https://animixplay.to/anime/22687"
      }
    },
    "YugenAnime": {
      "1643": {
        "identifier": "1643",
        "malId": 22687,
        "type": "anime",
        "page": "YugenAnime",
        "title": "Terra Formars",
        "url": "https://yugen.to/anime/1643/terra-formars/"
      }
    },
    "Zoro": {
      "3410": {
        "identifier": "3410",
        "malId": 22687,
        "type": "anime",
        "page": "Zoro",
        "title": "Terra Formars",
        "url": "https://zoro.to/terra-formars-3410"
      }
    }
  }
}