{
  "createdAt": "2020-10-12T15:39:35.000Z",
  "updatedAt": "2022-04-03T05:03:12.000Z",
  "checkedAt": null,
  "id": 30232,
  "type": "anime",
  "title": "Tamagotchi! Tamatomo Daishuu GO",
  "altTitle": [
    "Tamagotchi! Tamatomo Dai Shu-GO",
    "たまごっち! たまともだいしゅーGO"
  ],
  "url": "https://myanimelist.net/anime/30232/Tamagotchi_Tamatomo_Daishuu_GO",
  "image": "https://cdn.myanimelist.net/images/anime/12/72478.jpg",
  "category": "TV",
  "hentai": false,
  "externalLinks": [
    {
      "site": "officialsite",
      "url": "http://www.tv-tokyo.co.jp/anime/tamagotchi/"
    },
    {
      "site": "animedb",
      "url": "http://anidb.info/perl-bin/animedb.pl?show=anime&aid=11145"
    },
    {
      "site": "animenewsnetwork",
      "url": "http://www.animenewsnetwork.com/encyclopedia/anime.php?id=16861"
    },
    {
      "site": "wikipedia",
      "url": "http://en.wikipedia.org/wiki/Tamagotchi!_(anime)"
    }
  ],
  "legalLinks": [],
  "deletedAt": null,
  "anidbId": 11145,
  "Pages": {}
}