{
  "createdAt": "2020-10-12T15:39:40.000Z",
  "updatedAt": "2022-05-14T16:43:35.000Z",
  "checkedAt": "2022-05-14T16:43:35.000Z",
  "id": 31838,
  "type": "anime",
  "title": "Ze Tian Ji",
  "altTitle": [
    "Way of Choices",
    "Fighter of the Destiny",
    "择天记"
  ],
  "url": "https://myanimelist.net/anime/31838/Ze_Tian_Ji",
  "image": "https://cdn.myanimelist.net/images/anime/3/79002.jpg",
  "category": "ONA",
  "hentai": false,
  "externalLinks": [
    {
      "site": "officialsite",
      "url": "http://weibo.com/zetianji"
    },
    {
      "site": "animedb",
      "url": "http://anidb.info/perl-bin/animedb.pl?show=anime&aid=13466"
    }
  ],
  "legalLinks": [],
  "deletedAt": null,
  "anidbId": 13466,
  "Pages": {
    "9anime": {
      "40z7": {
        "createdAt": "2020-10-12T15:49:59.000Z",
        "updatedAt": "2021-05-20T15:21:50.000Z",
        "checkedAt": null,
        "id": 2041,
        "identifier": "40z7",
        "type": "anime",
        "page": "9anime",
        "title": "Ze Tian Ji",
        "url": "https://9anime.to/watch/ze-tian-ji.40z7",
        "image": "https://images2-focus-opensocial.googleusercontent.com/gadgets/proxy?container=focus&amp;gadget=a&amp;no_expand=1&amp;refresh=604800&amp;url=http://2.bp.blogspot.com/-l5jJLByFEG4/Wd5zfA73ZKI/AAAAAAAACdM/WrDtOp_NdW4-Vm7KbFjw0-sRNfjaeO_8wCHMYCw/s0/",
        "hentai": false,
        "sticky": false,
        "active": true,
        "actorId": null,
        "malId": 31838,
        "aniId": 101409,
        "deletedAt": null
      }
    },
    "Gogoanime": {
      "ze-tian-ji": {
        "createdAt": "2020-10-12T16:02:21.000Z",
        "updatedAt": "2021-05-20T15:21:55.000Z",
        "checkedAt": null,
        "id": 21656,
        "identifier": "ze-tian-ji",
        "type": "anime",
        "page": "Gogoanime",
        "title": "Ze Tian Ji",
        "url": "https://gogoanime.vc/category/ze-tian-ji",
        "image": "https://images.gogoanime.tv/cover/ze-tian-ji.png",
        "hentai": false,
        "sticky": false,
        "active": true,
        "actorId": null,
        "malId": 31838,
        "aniId": 101409,
        "deletedAt": null
      },
      "ze-tian-ji-s3": {
        "createdAt": "2020-10-12T16:02:22.000Z",
        "updatedAt": "2021-05-20T15:21:55.000Z",
        "checkedAt": null,
        "id": 21660,
        "identifier": "ze-tian-ji-s3",
        "type": "anime",
        "page": "Gogoanime",
        "title": "Ze Tian Ji S3",
        "url": "https://gogoanime.vc/category/ze-tian-ji-s3",
        "image": "https://gogocdn.net/cover/ze-tian-ji-s3.png",
        "hentai": false,
        "sticky": false,
        "active": true,
        "actorId": null,
        "malId": 31838,
        "aniId": 101409,
        "deletedAt": null
      }
    },
    "AniMixPlay": {
      "31838": {
        "identifier": "31838",
        "malId": 31838,
        "type": "anime",
        "page": "AniMixPlay",
        "title": "Ze Tian Ji",
        "url": "https://animixplay.to/anime/31838"
      }
    },
    "YugenAnime": {
      "2034": {
        "identifier": "2034",
        "malId": 31838,
        "type": "anime",
        "page": "YugenAnime",
        "title": "Ze Tian Ji",
        "url": "https://yugen.to/anime/2034/ze-tian-ji/"
      }
    },
    "Zoro": {
      "4099": {
        "identifier": "4099",
        "malId": 31838,
        "type": "anime",
        "page": "Zoro",
        "title": "Ze Tian Ji",
        "url": "https://zoro.to/ze-tian-ji-4099"
      }
    }
  }
}