{
  "createdAt": "2020-10-12T15:39:47.000Z",
  "updatedAt": "2022-05-14T21:42:53.000Z",
  "checkedAt": "2022-05-14T21:42:53.000Z",
  "id": 33795,
  "type": "anime",
  "title": "Mahou Shoujo Nante Mou Ii Desukara. Second Season",
  "altTitle": [
    "Mahou Shoujo Nante Mouiidesukara.",
    "Mahou Shoujo Nante Mouiidesukara Second Season",
    "魔法少女なんてもういいですから。 セカンドシーズン"
  ],
  "url": "https://myanimelist.net/anime/33795/Mahou_Shoujo_Nante_Mou_Ii_Desukara_Second_Season",
  "image": "https://cdn.myanimelist.net/images/anime/5/82253.jpg",
  "category": "TV",
  "hentai": false,
  "externalLinks": [
    {
      "site": "officialsite",
      "url": "http://mouiidesukara.com/"
    },
    {
      "site": "animedb",
      "url": "http://anidb.info/perl-bin/animedb.pl?show=anime&aid=12317"
    },
    {
      "site": "animenewsnetwork",
      "url": "http://www.animenewsnetwork.com/encyclopedia/anime.php?id=18681"
    },
    {
      "site": "wikipedia",
      "url": "https://en.wikipedia.org/wiki/Mahou_Shoujo_Nante_Mouiidesukara"
    }
  ],
  "legalLinks": [
    {
      "site": "crunchyroll",
      "url": "http://www.crunchyroll.com/series-269069"
    }
  ],
  "deletedAt": null,
  "anidbId": 12317,
  "Pages": {
    "9anime": {
      "mo07": {
        "createdAt": "2020-10-12T15:53:33.000Z",
        "updatedAt": "2021-05-20T15:21:52.000Z",
        "checkedAt": null,
        "id": 6651,
        "identifier": "mo07",
        "type": "anime",
        "page": "9anime",
        "title": "Mahou Shoujo Nante Mou Ii Desukara. 2nd Season",
        "url": "https://9anime.to/watch/mahou-shoujo-nante-mou-ii-desukara-2nd-season.mo07",
        "image": "https://images2-focus-opensocial.googleusercontent.com/gadgets/proxy?container=focus&amp;gadget=a&amp;no_expand=1&amp;refresh=604800&amp;url=http://2.bp.blogspot.com/-eIFMBF0R2vo/V-tyCWo5nOI/AAAAAAABBy0/5xTpLEqL8JQ/s0/",
        "hentai": false,
        "sticky": false,
        "active": true,
        "actorId": null,
        "malId": 33795,
        "aniId": 21892,
        "deletedAt": null
      }
    },
    "Gogoanime": {
      "mahou-shoujo-nante-mou-ii-desukara-2nd-season": {
        "createdAt": "2020-10-12T16:01:12.000Z",
        "updatedAt": "2021-05-20T15:21:54.000Z",
        "checkedAt": null,
        "id": 19274,
        "identifier": "mahou-shoujo-nante-mou-ii-desukara-2nd-season",
        "type": "anime",
        "page": "Gogoanime",
        "title": "Mahou Shoujo Nante Mou Ii Desukara. 2nd Season",
        "url": "https://gogoanime.vc/category/mahou-shoujo-nante-mou-ii-desukara-2nd-season",
        "image": "https://cdnimg.xyz/cover/mahou-shoujo-nante-mou-ii-desukara-2nd-season.png",
        "hentai": false,
        "sticky": false,
        "active": true,
        "actorId": null,
        "malId": 33795,
        "aniId": 21892,
        "deletedAt": null
      }
    },
    "animepahe": {
      "1386": {
        "identifier": "1386",
        "malId": 33795,
        "type": "anime",
        "page": "animepahe",
        "title": "Mahou Shoujo Nante Mou Ii Desukara. Second Season",
        "url": "https://animepahe.com/a/1386"
      }
    },
    "AniMixPlay": {
      "33795": {
        "identifier": "33795",
        "malId": 33795,
        "type": "anime",
        "page": "AniMixPlay",
        "title": "Mahou Shoujo Nante Mou Ii Desukara. Second Season",
        "url": "https://animixplay.to/anime/33795"
      }
    },
    "YugenAnime": {
      "6984": {
        "identifier": "6984",
        "malId": 33795,
        "type": "anime",
        "page": "YugenAnime",
        "title": "Mahou Shoujo Nante Mou Ii Desukara. Second Season",
        "url": "https://yugen.to/anime/6984/mahou-shoujo-nante-mou-ii-desukara-2nd-season/"
      }
    }
  }
}