{
  "createdAt": "2020-10-12T15:39:49.000Z",
  "updatedAt": "2022-05-14T19:34:59.000Z",
  "checkedAt": "2022-05-14T19:34:59.000Z",
  "id": 34204,
  "type": "anime",
  "title": "Hibike! Euphonium 2 Specials",
  "altTitle": [
    "Sound! Euphonium 2 Specials",
    "響け！ユーフォニアム2"
  ],
  "url": "https://myanimelist.net/anime/34204/Hibike_Euphonium_2_Specials",
  "image": "https://cdn.myanimelist.net/images/anime/13/83486.jpg",
  "category": "Special",
  "hentai": false,
  "externalLinks": [],
  "legalLinks": [],
  "deletedAt": null,
  "anidbId": null,
  "Pages": {
    "9anime": {
      "k19v": {
        "createdAt": "2020-10-12T15:52:23.000Z",
        "updatedAt": "2021-05-20T15:21:51.000Z",
        "checkedAt": null,
        "id": 5178,
        "identifier": "k19v",
        "type": "anime",
        "page": "9anime",
        "title": "Hibike! Euphonium 2 Specials",
        "url": "https://9anime.to/watch/hibike-euphonium-2-specials.k19v",
        "image": "https://images2-focus-opensocial.googleusercontent.com/gadgets/proxy?container=focus&amp;gadget=a&amp;no_expand=1&amp;refresh=604800&amp;url=http://2.bp.blogspot.com/-yuj47D0cafQ/WF4XhqZtrjI/AAAAAAABUY4/3pGPnaqplJY/s0/",
        "hentai": false,
        "sticky": false,
        "active": true,
        "actorId": null,
        "malId": 34204,
        "aniId": 98338,
        "deletedAt": null
      }
    },
    "Gogoanime": {
      "hibike-euphonium-2-specials": {
        "createdAt": "2020-10-12T16:00:42.000Z",
        "updatedAt": "2021-05-20T15:21:54.000Z",
        "checkedAt": null,
        "id": 18260,
        "identifier": "hibike-euphonium-2-specials",
        "type": "anime",
        "page": "Gogoanime",
        "title": "Hibike! Euphonium 2 Specials",
        "url": "https://gogoanime.vc/category/hibike-euphonium-2-specials",
        "image": "https://cdnimg.xyz/cover/hibike-euphonium-2-specials.png",
        "hentai": false,
        "sticky": false,
        "active": true,
        "actorId": null,
        "malId": 34204,
        "aniId": 98338,
        "deletedAt": null
      }
    },
    "animepahe": {
      "2968": {
        "identifier": "2968",
        "malId": 34204,
        "type": "anime",
        "page": "animepahe",
        "title": "Hibike! Euphonium 2 Specials",
        "url": "https://animepahe.com/a/2968"
      }
    },
    "AniMixPlay": {
      "34204": {
        "identifier": "34204",
        "malId": 34204,
        "type": "anime",
        "page": "AniMixPlay",
        "title": "Hibike! Euphonium 2 Specials",
        "url": "https://animixplay.to/anime/34204"
      }
    },
    "YugenAnime": {
      "1459": {
        "identifier": "1459",
        "malId": 34204,
        "type": "anime",
        "page": "YugenAnime",
        "title": "Hibike! Euphonium 2 Specials",
        "url": "https://yugen.to/anime/1459/hibike-euphonium-2-specials/"
      }
    },
    "Zoro": {
      "4988": {
        "identifier": "4988",
        "malId": 34204,
        "type": "anime",
        "page": "Zoro",
        "title": "Sound! Euphonium 2 Specials",
        "url": "https://zoro.to/sound-euphonium-2-specials-4988"
      }
    }
  }
}