{
  "createdAt": "2020-10-12T15:40:09.000Z",
  "updatedAt": "2022-05-14T16:01:57.000Z",
  "checkedAt": "2022-05-14T16:01:57.000Z",
  "id": 39539,
  "type": "anime",
  "title": "No Guns Life",
  "altTitle": [
    "No Guns Life",
    "ノー・ガンズ・ライフ"
  ],
  "url": "https://myanimelist.net/anime/39539/No_Guns_Life",
  "image": "https://cdn.myanimelist.net/images/anime/1531/102113.jpg",
  "category": "TV",
  "hentai": false,
  "externalLinks": [
    {
      "site": "officialsite",
      "url": "http://nogunslife.com/"
    },
    {
      "site": "animedb",
      "url": "http://anidb.info/perl-bin/animedb.pl?show=anime&aid=14759"
    },
    {
      "site": "animenewsnetwork",
      "url": "http://www.animenewsnetwork.com/encyclopedia/anime.php?id=21978"
    },
    {
      "site": "wikipedia",
      "url": "https://en.wikipedia.org/wiki/No_Guns_Life#Anime"
    }
  ],
  "legalLinks": [
    {
      "site": "crunchyroll",
      "url": "http://www.crunchyroll.com/series-281973"
    },
    {
      "site": "funimation",
      "url": "https://www.funimation.com/shows/no-guns-life"
    },
    {
      "site": "netflix",
      "url": "https://www.netflix.com/"
    }
  ],
  "deletedAt": null,
  "anidbId": 14759,
  "Pages": {
    "9anime": {
      "4p3o": {
        "createdAt": "2020-10-12T15:50:11.000Z",
        "updatedAt": "2022-03-19T19:19:12.000Z",
        "checkedAt": null,
        "id": 2334,
        "identifier": "4p3o",
        "type": "anime",
        "page": "9anime",
        "title": "No Guns Life",
        "url": "https://9anime.to/watch/no-guns-life.4p3o",
        "image": "https://static.bunnycdn.ru/i/cache/images/2019/10/2eb393091ef6d24d1ebdba981bc1490e.jpg",
        "hentai": false,
        "sticky": false,
        "active": true,
        "actorId": null,
        "malId": 39539,
        "aniId": 108478,
        "deletedAt": null
      },
      "7q57": {
        "createdAt": "2020-10-12T15:51:12.000Z",
        "updatedAt": "2021-05-20T15:21:51.000Z",
        "checkedAt": null,
        "id": 3539,
        "identifier": "7q57",
        "type": "anime",
        "page": "9anime",
        "title": "No Guns Life (Dub)",
        "url": "https://9anime.to/watch/no-guns-life-dub.7q57",
        "image": "https://static.akacdn.ru/files/images/2019/10/42c277490acab4a28806f13150b573e5.jpg",
        "hentai": false,
        "sticky": false,
        "active": true,
        "actorId": null,
        "malId": 39539,
        "aniId": 108478,
        "deletedAt": null
      }
    },
    "Gogoanime": {
      "no-guns-life": {
        "createdAt": "2020-10-12T16:01:26.000Z",
        "updatedAt": "2021-05-20T15:21:54.000Z",
        "checkedAt": null,
        "id": 19760,
        "identifier": "no-guns-life",
        "type": "anime",
        "page": "Gogoanime",
        "title": "No Guns Life",
        "url": "https://gogoanime.vc/category/no-guns-life",
        "image": "https://cdnimg.xyz/cover/no-guns-life.png",
        "hentai": false,
        "sticky": false,
        "active": true,
        "actorId": null,
        "malId": 39539,
        "aniId": 108478,
        "deletedAt": null
      },
      "no-guns-life-dub": {
        "createdAt": "2020-10-12T16:01:26.000Z",
        "updatedAt": "2021-05-20T15:21:54.000Z",
        "checkedAt": null,
        "id": 19763,
        "identifier": "no-guns-life-dub",
        "type": "anime",
        "page": "Gogoanime",
        "title": "No Guns Life (Dub)",
        "url": "https://gogoanime.vc/category/no-guns-life-dub",
        "image": "https://cdnimg.xyz/cover/no-guns-life-dub.png",
        "hentai": false,
        "sticky": false,
        "active": true,
        "actorId": null,
        "malId": 39539,
        "aniId": 108478,
        "deletedAt": null
      }
    },
    "animepahe": {
      "3443": {
        "identifier": "3443",
        "malId": 39539,
        "type": "anime",
        "page": "animepahe",
        "title": "No Guns Life",
        "url": "https://animepahe.com/a/3443"
      }
    },
    "AniMixPlay": {
      "39539": {
        "identifier": "39539",
        "malId": 39539,
        "type": "anime",
        "page": "AniMixPlay",
        "title": "No Guns Life",
        "url": "https://animixplay.to/anime/39539"
      }
    },
    "YugenAnime": {
      "1578": {
        "identifier": "1578",
        "malId": 39539,
        "type": "anime",
        "page": "YugenAnime",
        "title": "No Guns Life",
        "url": "https://yugen.to/anime/1578/no-guns-life/"
      }
    },
    "Zoro": {
      "3937": {
        "identifier": "3937",
        "malId": 39539,
        "type": "anime",
        "page": "Zoro",
        "title": "No Guns Life",
        "url": "https://zoro.to/no-guns-life-3937"
      }
    }
  }
}