{
  "createdAt": "2022-06-03T13:30:01.082Z",
  "updatedAt": "2022-06-03T13:30:01.082Z",
  "checkedAt": "2022-06-03T13:30:01.000Z",
  "id": 40282,
  "type": "anime",
  "title": "Nendo no Tatakai (2019)",
  "altTitle": [
    "Battle of Clay",
    "ねんどのたたかい"
  ],
  "url": "https://myanimelist.net/anime/40282/Nendo_no_Tatakai_2019",
  "image": "https://cdn.myanimelist.net/images/anime/1740/102716.jpg",
  "category": "ONA",
  "hentai": false,
  "externalLinks": [
    {
      "site": "officialsite",
      "url": "https://www.youtube.com/watch?v=ak6tUo_rvbo"
    },
    {
      "site": "animedb",
      "url": "http://anidb.info/perl-bin/animedb.pl?show=anime&aid=15053"
    },
    {
      "site": "wikipedia",
      "url": "https://ja.wikipedia.org/wiki/%E3%81%A6%E3%81%84%E3%81%88%E3%81%AC"
    }
  ],
  "legalLinks": [],
  "deletedAt": null,
  "anidbId": 15053,
  "Pages": {
    "Zoro": {
      "10620": {
        "identifier": "10620",
        "malId": 40282,
        "type": "anime",
        "page": "Zoro",
        "title": "Battle of Clay",
        "url": "https://zoro.to/battle-of-clay-10620"
      }
    }
  }
}