{
  "createdAt": "2021-02-01T03:31:54.000Z",
  "updatedAt": "2022-05-14T17:09:35.000Z",
  "checkedAt": "2022-05-14T17:09:35.000Z",
  "id": 47160,
  "type": "anime",
  "title": "Goblin Slayer 2nd Season",
  "altTitle": [
    "ゴブリンスレイヤー"
  ],
  "url": "https://myanimelist.net/anime/47160/Goblin_Slayer_2nd_Season",
  "image": "https://cdn.myanimelist.net/images/anime/1488/122008.jpg",
  "category": "TV",
  "hentai": false,
  "externalLinks": [
    {
      "site": "officialsite",
      "url": "http://www.goblinslayer.jp/"
    },
    {
      "site": "animedb",
      "url": "http://anidb.info/perl-bin/animedb.pl?show=anime&aid=16027"
    },
    {
      "site": "wikipedia",
      "url": "https://en.wikipedia.org/wiki/Goblin_Slayer#Anime"
    }
  ],
  "legalLinks": [],
  "deletedAt": null,
  "anidbId": 16027,
  "Pages": {
    "AniMixPlay": {
      "47160": {
        "identifier": "47160",
        "malId": 47160,
        "type": "anime",
        "page": "AniMixPlay",
        "title": "Goblin Slayer 2nd Season",
        "url": "https://animixplay.to/anime/47160"
      }
    }
  }
}