{
  "createdAt": "2022-06-24T07:30:02.629Z",
  "updatedAt": "2022-06-24T07:30:02.629Z",
  "checkedAt": "2022-06-24T07:30:02.000Z",
  "id": 49894,
  "type": "anime",
  "title": "Eiyuu Kyoushitsu",
  "altTitle": [
    "Class Room✿For Heroes",
    "英雄教室"
  ],
  "url": "https://myanimelist.net/anime/49894/Eiyuu_Kyoushitsu",
  "image": "https://cdn.myanimelist.net/images/anime/1386/117935.jpg",
  "category": "TV",
  "hentai": false,
  "externalLinks": [
    {
      "site": "animedb",
      "url": "http://anidb.info/perl-bin/animedb.pl?show=anime&aid=16792"
    },
    {
      "site": "animenewsnetwork",
      "url": "http://www.animenewsnetwork.com/encyclopedia/anime.php?id=24762"
    },
    {
      "site": "wikipedia",
      "url": "https://en.wikipedia.org/wiki/Eiy%C5%AB_Ky%C5%8Dshitsu"
    }
  ],
  "legalLinks": [],
  "deletedAt": null,
  "anidbId": 16792,
  "Pages": {
    "AniMixPlay": {
      "49894": {
        "identifier": "49894",
        "malId": 49894,
        "type": "anime",
        "page": "AniMixPlay",
        "title": "Eiyuu Kyoushitsu",
        "url": "https://animixplay.to/anime/49894"
      }
    }
  }
}