{
  "createdAt": "2020-10-12T15:38:49.000Z",
  "updatedAt": "2022-05-15T01:37:55.000Z",
  "checkedAt": "2022-05-15T01:37:55.000Z",
  "id": 5997,
  "type": "anime",
  "title": "Sabu to Ichi Torimono Hikae",
  "altTitle": [
    "Sabu & Ichi's Arrest Note",
    "Sabu & Ichi's Arrest Warrant",
    "佐武と市捕物控"
  ],
  "url": "https://myanimelist.net/anime/5997/Sabu_to_Ichi_Torimono_Hikae",
  "image": "https://cdn.myanimelist.net/images/anime/9/84054.jpg",
  "category": "TV",
  "hentai": false,
  "externalLinks": [
    {
      "site": "animedb",
      "url": "http://anidb.info/perl-bin/animedb.pl?show=anime&aid=5293"
    },
    {
      "site": "animenewsnetwork",
      "url": "http://www.animenewsnetwork.com/encyclopedia/anime.php?id=2374"
    },
    {
      "site": "wikipedia",
      "url": "http://en.wikipedia.org/wiki/Sabu_to_Ichi_Torimono_Hikae"
    }
  ],
  "legalLinks": [],
  "deletedAt": null,
  "anidbId": 5293,
  "Pages": {
    "9anime": {
      "r64o": {
        "createdAt": "2020-10-12T15:55:29.000Z",
        "updatedAt": "2021-05-20T15:21:52.000Z",
        "checkedAt": null,
        "id": 8790,
        "identifier": "r64o",
        "type": "anime",
        "page": "9anime",
        "title": "Sabu to Ichi Torimono Hikae",
        "url": "https://9anime.to/watch/sabu-to-ichi-torimono-hikae.r64o",
        "image": "https://images2-focus-opensocial.googleusercontent.com/gadgets/proxy?container=focus&amp;gadget=a&amp;no_expand=1&amp;refresh=604800&amp;url=http://2.bp.blogspot.com/-mqRpnoYKfXk/WF_eB9odvqI/AAAAAAABUnE/IOT5Vy6Z3uE/s0/",
        "hentai": false,
        "sticky": false,
        "active": true,
        "actorId": null,
        "malId": 5997,
        "aniId": 5997,
        "deletedAt": null
      }
    },
    "Gogoanime": {
      "sabu-to-ichi-torimono-hikae": {
        "createdAt": "2020-10-12T16:01:44.000Z",
        "updatedAt": "2021-05-20T15:21:54.000Z",
        "checkedAt": null,
        "id": 20356,
        "identifier": "sabu-to-ichi-torimono-hikae",
        "type": "anime",
        "page": "Gogoanime",
        "title": "Sabu to Ichi Torimono Hikae",
        "url": "https://gogoanime.vc/category/sabu-to-ichi-torimono-hikae",
        "image": "https://cdnimg.xyz/cover/sabu-to-ichi-torimono-hikae.png",
        "hentai": false,
        "sticky": false,
        "active": true,
        "actorId": null,
        "malId": 5997,
        "aniId": 5997,
        "deletedAt": null
      }
    },
    "AniMixPlay": {
      "5997": {
        "identifier": "5997",
        "malId": 5997,
        "type": "anime",
        "page": "AniMixPlay",
        "title": "Sabu to Ichi Torimono Hikae",
        "url": "https://animixplay.to/anime/5997"
      }
    },
    "YugenAnime": {
      "6136": {
        "identifier": "6136",
        "malId": 5997,
        "type": "anime",
        "page": "YugenAnime",
        "title": "Sabu to Ichi Torimono Hikae",
        "url": "https://yugen.to/anime/6136/sabu-to-ichi-torimono-hikae/"
      }
    }
  }
}