{
  "createdAt": "2020-10-12T15:39:01.000Z",
  "updatedAt": "2022-05-14T16:02:22.000Z",
  "checkedAt": "2022-05-14T16:02:22.000Z",
  "id": 9041,
  "type": "anime",
  "title": "IS: Infinite Stratos",
  "altTitle": [
    "IS",
    "Infinite Stratos",
    "IS 〈インフィニット・ストラトス〉"
  ],
  "url": "https://myanimelist.net/anime/9041/IS__Infinite_Stratos",
  "image": "https://cdn.myanimelist.net/images/anime/3/74045.jpg",
  "category": "TV",
  "hentai": false,
  "externalLinks": [
    {
      "site": "officialsite",
      "url": "http://www.tbs.co.jp/anime/is/"
    },
    {
      "site": "animedb",
      "url": "http://anidb.info/perl-bin/animedb.pl?show=anime&aid=7727"
    },
    {
      "site": "animenewsnetwork",
      "url": "http://www.animenewsnetwork.com/encyclopedia/anime.php?id=11769"
    },
    {
      "site": "wikipedia",
      "url": "http://en.wikipedia.org/wiki/IS_%28Infinite_Stratos%29"
    }
  ],
  "legalLinks": [
    {
      "site": "hidive",
      "url": "https://www.hidive.com/tv/infinite-stratos"
    }
  ],
  "deletedAt": null,
  "anidbId": 7727,
  "Pages": {
    "9anime": {
      "o7y": {
        "createdAt": "2020-10-12T15:54:09.000Z",
        "updatedAt": "2021-05-20T15:21:52.000Z",
        "checkedAt": null,
        "id": 7447,
        "identifier": "o7y",
        "type": "anime",
        "page": "9anime",
        "title": "IS: Infinite Stratos",
        "url": "https://9anime.to/watch/is-infinite-stratos.o7y",
        "image": "https://images2-focus-opensocial.googleusercontent.com/gadgets/proxy?container=focus&amp;gadget=a&amp;no_expand=1&amp;refresh=604800&amp;url=http://2.bp.blogspot.com/-PsW9xVWA8VI/V4Ehu0FaQcI/AAAAAAAAuRY/Oa4m9bZxCvU/s0/",
        "hentai": false,
        "sticky": false,
        "active": true,
        "actorId": null,
        "malId": 9041,
        "aniId": 9041,
        "deletedAt": null
      }
    },
    "Gogoanime": {
      "infinite-stratos": {
        "createdAt": "2020-10-12T16:00:49.000Z",
        "updatedAt": "2021-05-20T15:21:54.000Z",
        "checkedAt": null,
        "id": 18472,
        "identifier": "infinite-stratos",
        "type": "anime",
        "page": "Gogoanime",
        "title": "Infinite Stratos",
        "url": "https://gogoanime.vc/category/infinite-stratos",
        "image": "https://images.gogoanime.tv/images/anime/I/Infinite-Stratos.jpg",
        "hentai": false,
        "sticky": false,
        "active": true,
        "actorId": null,
        "malId": 9041,
        "aniId": 9041,
        "deletedAt": null
      },
      "is-infinite-stratos-dub": {
        "createdAt": "2020-10-12T16:00:50.000Z",
        "updatedAt": "2021-05-20T15:21:54.000Z",
        "checkedAt": null,
        "id": 18514,
        "identifier": "is-infinite-stratos-dub",
        "type": "anime",
        "page": "Gogoanime",
        "title": "IS: Infinite Stratos (Dub)",
        "url": "https://gogoanime.vc/category/is-infinite-stratos-dub",
        "image": "https://cdnimg.xyz/cover/is-infinite-stratos-dub.png",
        "hentai": false,
        "sticky": false,
        "active": true,
        "actorId": null,
        "malId": 9041,
        "aniId": 9041,
        "deletedAt": null
      }
    },
    "animepahe": {
      "65": {
        "identifier": "65",
        "malId": 9041,
        "type": "anime",
        "page": "animepahe",
        "title": "IS: Infinite Stratos",
        "url": "https://animepahe.com/a/65"
      }
    },
    "AniMixPlay": {
      "9041": {
        "identifier": "9041",
        "malId": 9041,
        "type": "anime",
        "page": "AniMixPlay",
        "title": "IS: Infinite Stratos",
        "url": "https://animixplay.to/anime/9041"
      }
    },
    "YugenAnime": {
      "2719": {
        "identifier": "2719",
        "malId": 9041,
        "type": "anime",
        "page": "YugenAnime",
        "title": "IS: Infinite Stratos",
        "url": "https://yugen.to/anime/2719/is-infinite-stratos/"
      }
    },
    "Zoro": {
      "4398": {
        "identifier": "4398",
        "malId": 9041,
        "type": "anime",
        "page": "Zoro",
        "title": "Infinite Stratos",
        "url": "https://zoro.to/infinite-stratos-4398"
      }
    }
  }
}