{
  "createdAt": "2022-07-28T20:30:00.275Z",
  "updatedAt": "2022-07-29T08:07:10.000Z",
  "checkedAt": "2022-07-28T20:30:00.000Z",
  "id": 41729,
  "identifier": "bei-kun-bai-wan-nian-dizi-bianbu-zhu-tian-wan-jie",
  "type": "anime",
  "page": "Gogoanime",
  "title": "Bei Kun Bai Wan Nian: Dizi Bianbu Zhu Tian Wan Jie",
  "url": "https://gogoanime.lu/category/bei-kun-bai-wan-nian-dizi-bianbu-zhu-tian-wan-jie",
  "image": "https://gogocdn.net/cover/bei-kun-bai-wan-nian-dizi-bianbu-zhu-tian-wan-jie.png",
  "hentai": false,
  "sticky": false,
  "active": true,
  "actorId": 1,
  "malId": null,
  "aniId": null,
  "deletedAt": null,
  "Mal": null,
  "Ani": null
}